tools/__init__.py
tools/packpy/__init__.py
tools/packpy/object.py
tools/packpy/secrets.py
tools/packpy/settings.py
tools/packpy/uploader.py
xvg/__init__.py
xvg/application/__init__.py
xvg/application/engine.py
xvg/contexts/__init__.py
xvg/contexts/context.py
xvg/contexts/purecontext.py
xvg/core/__init__.py
xvg/core/encoding.py
xvg/core/error.py
xvg/core/filedata.py
xvg/core/filepath.py
xvg/core/filetype.py
xvg/core/json.py
xvg/core/list.py
xvg/core/object.py
xvg/core/query.py
xvg/core/reflection.py
xvg/core/string.py
xvg/interpreters/__init__.py
xvg/interpreters/execinterpreter.py
xvg/interpreters/interpreter.py
xvg/math/__init__.py
xvg/math/ellipse.py
xvg/math/matrix.py
xvg/math/polygon.py
xvg/math/random.py
xvg/math/rectangle.py
xvg/math/spline.py
xvg/math/vector.py
xvg/models/__init__.py
xvg/models/color.py
xvg/models/filter.py
xvg/models/font.py
xvg/models/form.py
xvg/models/group.py
xvg/models/image.py
xvg/models/mask.py
xvg/models/path.py
xvg/models/point.py
xvg/models/text.py
xvg/renderers/__init__.py
xvg/renderers/jsonrenderer.py
xvg/renderers/svgrenderer.py
xvg-2020.4.2.1.dist-info/LICENSE
xvg-2020.4.2.1.dist-info/METADATA
xvg-2020.4.2.1.dist-info/WHEEL
xvg-2020.4.2.1.dist-info/top_level.txt
xvg-2020.4.2.1.dist-info/RECORD
